compcate/__init__.py
compcate/comention.py
compcate-0.0.3.dist-info/LICENSE
compcate-0.0.3.dist-info/METADATA
compcate-0.0.3.dist-info/WHEEL
compcate-0.0.3.dist-info/top_level.txt
compcate-0.0.3.dist-info/RECORD
