Metadata-Version: 2.1
Name: compcate
Version: 0.0.3
Summary: Identify and categorise corporate competitors
Author: tian han
Author-email: <tianhanuk@gmail.com>
Keywords: corporate competitors,strategic groups
Classifier: Development Status :: 1 - Planning
Classifier: Intended Audience :: Developers
Classifier: Programming Language :: Python :: 3
Classifier: Operating System :: Unix
Classifier: Operating System :: MacOS :: MacOS X
Classifier: Operating System :: Microsoft :: Windows
License-File: LICENSE
Requires-Dist: cdlib
Requires-Dist: leidenalg
